{
  "project_info": {
    "project_number": "913191149764",
    "project_id": "blackjackspecial-9e4ba",
    "storage_bucket": "blackjackspecial-9e4ba.appspot.com"
  },
  "client": [
    {
      "client_info": {
        "mobilesdk_app_id": "1:913191149764:android:b2eeaf5343e5edef2ba991",
        "android_client_info": {
          "package_name": "com.arodmar432p.blackjackspecial"
        }
      },
      "oauth_client": [],
      "api_key": [
        {
          "current_key": "AIzaSyBph--nIdhPpslYXKQLf7H_0o9XoCVLTGE"
        }
      ],
      "services": {
        "appinvite_service": {
          "other_platform_oauth_client": []
        }
      }
    }
  ],
  "configuration_version": "1"
}